Metadata-Version: 2.1
Name: django-unicorn-gbusby
Version: 0.50.3
Summary: (Fork)A magical full-stack framework for Django.
Home-page: https://www.django-unicorn.com
License: MIT
Keywords: django,python,javascript,fullstack
Author: Adam Hill
Author-email: unicorn@adamghill.com
Requires-Python: >=3.7,<4
Classifier: License :: OSI Approved :: MIT License
Classifier: Programming Language :: Python :: 3
Classifier: Programming Language :: Python :: 3.7
Classifier: Programming Language :: Python :: 3.8
Classifier: Programming Language :: Python :: 3.9
Classifier: Programming Language :: Python :: 3.10
Classifier: Programming Language :: Python :: 3.11
Provides-Extra: docs
Provides-Extra: minify
Requires-Dist: Sphinx (>=4.3.2,<5.0.0); extra == "docs"
Requires-Dist: beautifulsoup4 (>=4.8.0)
Requires-Dist: cachetools (>=4.1.1,<5.0.0)
Requires-Dist: dataclasses (>=0.8.0,<0.9.0); python_version < "3.7"
Requires-Dist: decorator (>=4.4.2,<5.0.0)
Requires-Dist: django (>=2.2)
Requires-Dist: furo (>=2021.11.23,<2022.0.0); extra == "docs"
Requires-Dist: htmlmin (>=0.1.12,<0.2.0); extra == "minify"
Requires-Dist: linkify-it-py (>=1.0.3,<2.0.0); extra == "docs"
Requires-Dist: myst-parser (>=0.16.1,<0.17.0); extra == "docs"
Requires-Dist: orjson (>=3.6.0,<4.0.0)
Requires-Dist: rst2pdf (>=0.98,<0.99); extra == "docs"
Requires-Dist: shortuuid (>=1.0.1,<2.0.0)
Requires-Dist: sphinx-autobuild (>=2021.3.14,<2022.0.0); extra == "docs"
Requires-Dist: sphinx-copybutton (>=0.4.0,<0.5.0); extra == "docs"
Project-URL: Documentation, https://www.django-unicorn.com/docs/
Project-URL: Funding, https://github.com/sponsors/adamghill
Project-URL: Repository, https://github.com/bazubii/django-unicorn/
